{"data":{"propertyOrder":{},"properties":{"name":{"name":"name","reference":"scalar","getter":false,"setter":false,"type":"string"},"type":{"name":"type","reference":"scalar","getter":false,"setter":false,"type":"string"},"patient":{"name":"patient","reference":"1:1","cascade":["persist"],"type":"Patient","owner":true,"nullable":false,"unique":true},"isConnect":{"name":"isConnect","reference":"scalar","default":false,"getter":false,"setter":false,"type":"boolean"}},"props":[{"name":"name","reference":"scalar","getter":false,"setter":false,"type":"string"},{"name":"type","reference":"scalar","getter":false,"setter":false,"type":"string"},{"name":"patient","reference":"1:1","cascade":["persist"],"type":"Patient","owner":true,"nullable":false,"unique":true},{"name":"isConnect","reference":"scalar","default":false,"getter":false,"setter":false,"type":"boolean"}],"primaryKeys":[],"filters":{},"hooks":{},"indexes":[],"uniques":[],"checks":[],"concurrencyCheckKeys":{},"className":"Device","path":"./src/device/entities/device.entity.ts","name":"Device","abstract":false,"constructorParams":[],"toJsonParams":[],"extends":"BaseEntity","useCache":true,"relations":[{"name":"patient","reference":"1:1","cascade":["persist"],"type":"Patient","owner":true,"nullable":false,"unique":true}],"collection":"device"},"origin":"./src/device/entities/device.entity.ts","hash":"bc805141320ae68dbb7887e6d1c783d9","version":"5.1.5"}
